{"abyssal-blade": {"name": 1, "price": "6650", "attr_": ["['+', '25', 'Damage', '+', '250', 'Health', '+', '10.0', 'HP', 'Regeneration', '+', '10', 'Strength']"], "buildto": [], "buildfrom": ["Builds from 2,150 2,950 1,550"], "description": ["Active:", "Overwhelm", "Stuns", "a", "target", "enemy", "unit", "for", "2.0", "seconds.", "Pierces", "Spell", "Immunity.", "Range:", "140", "Passive:", "Bash", "Grants", "melee", "heroes", "a", "25%", "chance", "on", "hit", "to", "stun", "the", "target", "for", "1.5", "seconds", "and", "deal", "100", "bonus", "magical", "damage.", "Bash", "chance", "for", "ranged", "heroes", "is", "10%", ".", "Passive:", "Damage", "Block", "Grants", "a", "50%", "chance", "to", "block", "70", "damage", "from", "incoming", "attacks", "on", "melee", "heroes,", "and", "35", "damage", "on", "ranged.", "35", "75"], "position": []}, "aegis-of-the-immortal": {"name": 1, "price": [], "attr_": [], "buildto": [], "buildfrom": [], "description": ["Passive:", "Reincarnation", "Brings", "you", "to", "life", "with", "full", "health", "and", "mana", "5.0", "seconds", "after", "you", "die,", "at", "the", "location", "where", "you", "died.", "Reincarnation", "must", "be", "used", "within", "5", "minutes", "or", "Aegis", "of", "the", "Immortal", "disappears.", "If", "it", "expires,", "it", "will", "heal", "you", "over", "5", "seconds", "(dispels", "on", "damage)."], "position": []}, "aeon-disk": {"name": 1, "price": "3100", "attr_": ["['+', '300', 'Health', '+', '300', 'Mana']"], "buildto": [], "buildfrom": ["Builds from 900 1,100 1,100"], "description": ["Passive:", "Combo", "Breaker", "When", "you", "take", "damage", "and", "your", "health", "falls", "below", "70%", ",", "a", "strong", "dispel", "is", "applied", "and", "you", "gain", "a", "2.5", "second", "buff", "that", "provides", "+75%", "Status", "Resistance", "and", "causes", "all", "damage", "you", "deal", "and", "are", "dealt", "to", "be", "reduced", "to", "zero.", "Only", "triggers", "on", "player", "based", "damage.", "115"], "position": []}, "aether-lens": {"name": 1, "price": "2350", "attr_": ["['+', '450', 'Mana', '+', '3.0', 'Mana', 'Regeneration']"], "buildto": [], "buildfrom": ["Builds from 850 900 600"], "description": ["Passive:", "Aethereal", "Focus", "Increases", "targeted", "spell", "and", "item", "cast", "range", "by", "250", "."], "position": []}, "aghanims-blessing": {"name": 1, "price": "6000", "attr_": [], "buildto": [], "buildfrom": ["Builds from 4,200 1,800"], "description": ["Passive:", "Ultimate", "Upgrade", "Upgrades", "the", "ultimate,", "and", "some", "abilities,", "of", "all", "heroes."], "position": []}, "aghanims-scepter": {"name": 1, "price": "4200", "attr_": ["['+', '10', 'All', 'Attributes', '+', '175', 'Health', '+', '175', 'Mana']"], "buildto": ["Builds into 6,000"], "buildfrom": ["Builds from 1,000 1,000 1,000 1,200"], "description": ["Passive:", "Ultimate", "Upgrade", "Upgrades", "the", "ultimate,", "and", "some", "abilities,", "of", "all", "heroes."], "position": []}, "animal-courier": {"name": 1, "price": "50", "attr_": [], "buildto": [], "buildfrom": [], "description": ["Use:", "Deploy", "Courier", "Deploys", "a", "creature", "to", "carry", "items", "to", "and", "from", "your", "team's", "base."], "position": []}, "arcane-boots": {"name": 1, "price": "1400", "attr_": ["['+', '15%', 'Movement', 'Speed', '+', '250', 'Mana']"], "buildto": ["Builds into 5,475"], "buildfrom": ["Builds from 500 900"], "description": ["Active:", "Replenish", "Mana", "Restores", "160", "mana", "to", "all", "nearby", "allies.", "Radius:", "1200", "Movement", "speed", "bonuses", "from", "multiple", "pairs", "of", "boots", "do", "not", "stack.", "55"], "position": []}, "armlet-of-mordiggian": {"name": 1, "price": "2380", "attr_": ["['+', '9', 'Damage', '+', '25', 'Attack', 'Speed', '+', '5', 'Armor', '+', '5', 'HP', 'Regeneration']"], "buildto": [], "buildfrom": ["Builds from 430 900 500 550"], "description": ["Toggle:", "Unholy", "Strength", "When", "active,", "Unholy", "Strength", "grants", "+31", "damage,", "+25", "strength", "and", "+4", "armor,", "but", "drains", "54", "health", "per", "second.", "You", "cannot", "die", "from", "the", "health", "drain", "when", "Unholy", "Strength", "is", "activated,", "nor", "from", "the", "strength", "loss", "when", "Unholy", "Strength", "is", "deactivated."], "position": []}, "assault-cuirass": {"name": 1, "price": "5250", "attr_": ["['+', '30', 'Attack', 'Speed', '+', '10', 'Armor']"], "buildto": [], "buildfrom": ["Builds from 550 1,400 2,000 1,300"], "description": ["Passive:", "Assault", "Aura", "Grants", "25", "attack", "speed", "and", "5", "armor", "to", "nearby", "allied", "units", "and", "structures,", "and", "decreases", "nearby", "enemy", "unit", "and", "structure", "armor", "by", "-5", ".", "Radius:", "1200"], "position": []}, "band-of-elvenskin": {"name": 1, "price": "450", "attr_": ["['+', '6', 'Agility']"], "buildto": ["Builds into 2,050 1,900"], "buildfrom": [], "description": [], "position": []}, "battle-fury": {"name": 1, "price": "4400", "attr_": ["['+', '45', 'Damage', '+', '7.5', 'HP', 'Regeneration', '+', '3.75', 'Mana', 'Regeneration']"], "buildto": [], "buildfrom": ["Builds from 200 2,200 1,700 300"], "description": ["Active:", "Chop", "Tree/Ward", "Destroy", "a", "target", "tree", "or", "ward.", "Tree", "Cast", "Range:", "350", "Ward", "Cast", "Range:", "450", "Passive:", "Quell", "Increases", "attack", "damage", "against", "non-hero", "units", "by", "24", "for", "melee", "heroes,", "and", "7", "for", "ranged.", "Passive:", "Cleave", "Deals", "60%", "of", "attack", "damage", "as", "physical", "damage", "in", "a", "cone", "up", "to", "650", "around", "the", "target.", "(Melee", "Only)", "4"], "position": []}, "belt-of-strength": {"name": 1, "price": "450", "attr_": ["['+', '6', 'Strength']"], "buildto": ["Builds into 1,450 2,400 2,950 2,050"], "buildfrom": [], "description": [], "position": []}, "black-king-bar": {"name": 1, "price": "4050", "attr_": ["['+', '10', 'Strength', '+', '24', 'Damage']"], "buildto": [], "buildfrom": ["Builds from 1,600 1,000 1,450"], "description": ["Active:", "Avatar", "Grants", "Spell", "Immunity", "and", "100%", "Magic", "Damage", "Resistance.", "Duration", "decreases", "with", "each", "use.", "Duration:", "10.0", "/", "9.0", "/", "8.0", "/", "7.0", "/", "6.0", "/", "5.0", "Dispel", "Type:", "Basic", "Dispel", "70"], "position": []}, "blade-mail": {"name": 1, "price": "2200", "attr_": ["['+', '22', 'Damage', '+', '5', 'Armor', '+', '10', 'Intelligence']"], "buildto": [], "buildfrom": ["Builds from 1,200 550 450"], "description": ["Active:", "Damage", "Return", "For", "4.5", "seconds,", "duplicates", "any", "damage", "taken", "back", "to", "the", "unit", "that", "dealt", "the", "damage.", "25", "25"], "position": []}, "blade-of-alacrity": {"name": 1, "price": "1000", "attr_": ["['+', '10', 'Agility']"], "buildto": ["Builds into 4,200 2,050 3,150"], "buildfrom": [], "description": [], "position": []}, "blades-of-attack": {"name": 1, "price": "430", "attr_": ["['+', '9', 'Damage']"], "buildto": ["Builds into 1,480 2,130 2,380"], "buildfrom": [], "description": [], "position": []}, "blight-stone": {"name": 1, "price": "300", "attr_": [], "buildto": ["Builds into 3,500 1,175"], "buildfrom": [], "description": ["Passive:", "Lesser", "Corruption", "Your", "attacks", "reduce", "the", "target's", "armor", "by", "-2", "for", "8.0", "seconds."], "position": []}, "blink-dagger": {"name": 1, "price": "2250", "attr_": [], "buildto": [], "buildfrom": [], "description": ["Active:", "Blink", "Teleport", "to", "a", "target", "point", "up", "to", "1200", "units", "away.", "Blink", "Dagger", "cannot", "be", "used", "for", "3.0", "seconds", "after", "taking", "damage", "from", "an", "enemy", "hero", "or", "Roshan.", "15"], "position": []}, "bloodstone": {"name": 1, "price": "4900", "attr_": ["['+', '475', 'Health', '+', '425', 'Mana', '+', '6.0', 'HP', 'Regeneration', '+', '3.0', 'Mana', 'Regeneration', '+', '200%', 'Mana', 'Regeneration']"], "buildto": [], "buildfrom": ["Builds from 1,700 3,200"], "description": ["Active:", "Bloodpact", "Converts", "30%", "of", "your", "max", "mana", "to", "health", "regeneration", "over", "2.0", "seconds.", "Passive:", "Mana", "Battery", "Each", "charge", "provides", "0.3", "HP", "and", "MP", "regen.", "Nearby", "kills", "provide", "1", "charges.", "Dying", "causes", "you", "to", "lose", "3", "charges.", "Starts", "with", "14", "charges.", "250"], "position": []}, "bloodthorn": {"name": 1, "price": "7205", "attr_": ["['+', '25', 'Intelligence', '+', '30', 'Attack', 'Speed', '+', '68', 'Damage', '+', '5.5', 'Mana', 'Regeneration']"], "buildto": [], "buildfrom": ["Builds from 4,075 2,130 1,000"], "description": ["Active:", "Soul", "Rend", "Silences", "a", "target", "for", "5.0", "seconds.", "At", "the", "end", "of", "the", "silence,", "an", "additional", "30.0%", "of", "all", "damage", "taken", "during", "the", "silence", "will", "be", "dealt", "to", "the", "target", "as", "magical", "damage.", "All", "attacks", "on", "the", "silenced", "target", "will", "have", "True", "Strike", "and", "100.0%", "chance", "to", "crit", "for", "140.0%", "damage.", "Range:", "900", "Passive:", "Critical", "Strike", "Grants", "a", "20%", "chance", "for", "attacks", "to", "inflict", "175%", "damage.", "15", "100"], "position": []}, "boots-of-speed": {"name": 1, "price": "500", "attr_": ["['+', '15%', 'Movement', 'Speed']"], "buildto": ["Builds into 2,500 1,480 1,450 1,400 1,050"], "buildfrom": [], "description": ["Movement", "speed", "bonuses", "from", "multiple", "pairs", "of", "boots", "do", "not", "stack."], "position": []}, "boots-of-travel-level-2": {"name": 1, "price": "4500", "attr_": ["['+', '35%', 'Movement', 'Speed']"], "buildto": [], "buildfrom": ["Builds from 2,000 2,500"], "description": ["Active:", "Teleport", "Teleports", "you", "to", "any", "allied", "structure", "or", "unit,", "including", "heroes.", "Teleporting", "to", "a", "unit", "is", "interrupted", "if", "the", "target", "unit", "dies.", "Adds", "10", "seconds", "to", "the", "cooldown", "of", "Town", "Portal", "Scroll.", "Movement", "speed", "bonuses", "from", "multiple", "pairs", "of", "boots", "do", "not", "stack.", "45", "75"], "position": []}, "boots-of-travel": {"name": 1, "price": "2500", "attr_": ["['+', '32%', 'Movement', 'Speed']"], "buildto": ["Builds into 4,500"], "buildfrom": ["Builds from 500 2,000"], "description": ["Active:", "Teleport", "Teleports", "you", "to", "an", "allied", "non-hero", "unit", "or", "structure.", "Teleporting", "to", "a", "unit", "is", "interrupted", "if", "the", "target", "unit", "dies.", "Adds", "10", "seconds", "to", "the", "cooldown", "of", "Town", "Portal", "Scroll.", "Movement", "speed", "bonuses", "from", "multiple", "pairs", "of", "boots", "do", "not", "stack.", "45", "75"], "position": []}, "bottle": {"name": 1, "price": "650", "attr_": [], "buildto": [], "buildfrom": [], "description": ["Active:", "Regenerate", "Consumes", "a", "charge", "to", "restore", "125", "health", "and", "75", "mana", "over", "2.5", "seconds.", "If", "the", "hero", "is", "attacked", "by", "an", "enemy", "hero", "or", "Roshan,", "the", "effect", "is", "lost.", "The", "Bottle", "automatically", "refills", "at", "the", "fountain.", "Hold", "Control", "to", "use", "on", "an", "allied", "hero.", "Range:", "350", "Passive:", "Store", "Rune", "Runes", "can", "be", "stored", "in", "the", "bottle", "for", "later", "use", "by", "right-clicking", "them.", "Unused", "runes", "will", "automatically", "activate", "after", "2", "minutes.", "Using", "a", "stored", "rune", "fully", "refills", "the", "Bottle.", "0.5"], "position": []}, "bracer": {"name": 1, "price": "515", "attr_": ["['+', '6', 'Strength', '+', '3', 'Agility', '+', '3', 'Intelligence', '+', '6.0%', 'Magic', 'Resistance']"], "buildto": [], "buildfrom": ["Builds from 135 165 215"], "description": [], "position": []}, "broadsword": {"name": 1, "price": "1200", "attr_": ["['+', '18', 'Damage']"], "buildto": ["Builds into 2,200 2,130"], "buildfrom": [], "description": [], "position": []}, "buckler": {"name": 1, "price": "800", "attr_": ["['+', '5', 'Armor', '+', '2', 'All', 'Attributes']"], "buildto": ["Builds into 2,275 3,700"], "buildfrom": ["Builds from 550 50 200"], "description": ["Active:", "Armor", "Bonus", "Gives", "+2", "armor", "to", "all", "allied", "units.", "Lasts", "15.0", "seconds", "on", "heroes,", "30.0", "seconds", "on", "units.", "Radius:", "1200", "25", "10"], "position": []}, "butterfly": {"name": 1, "price": "5475", "attr_": ["['+', '35', 'Agility', '+', '25', 'Damage', '+', '35%', 'Evasion', '+', '30', 'Attack', 'Speed']"], "buildto": [], "buildfrom": ["Builds from 875 1,400 3,200"], "description": [], "position": []}, "chainmail": {"name": 1, "price": "550", "attr_": ["['+', '5', 'Armor']"], "buildto": ["Builds into 1,480 800 5,250 2,200 1,175"], "buildfrom": [], "description": [], "position": []}, "cheese": {"name": 1, "price": "1000", "attr_": [], "buildto": [], "buildfrom": [], "description": ["Use:", "Fondue", "Instantly", "restores", "2500", "health", "and", "1500", "mana.", "40"], "position": []}, "circlet": {"name": 1, "price": "165", "attr_": ["['+', '2', 'All', 'Attributes']"], "buildto": ["Builds into 515 515 515 875"], "buildfrom": [], "description": [], "position": []}, "clarity": {"name": 1, "price": "50", "attr_": [], "buildto": [], "buildfrom": [], "description": ["Use:", "Replenish", "Grants", "4.5", "mana", "regeneration", "to", "the", "target", "for", "50", "seconds.", "If", "the", "unit", "is", "attacked", "by", "an", "enemy", "hero", "or", "Roshan,", "the", "effect", "is", "lost.", "Range:", "250"], "position": []}, "claymore": {"name": 1, "price": "1400", "attr_": ["['+', '21', 'Damage']"], "buildto": ["Builds into 2,800 5,300"], "buildfrom": [], "description": [], "position": []}, "cloak": {"name": 1, "price": "550", "attr_": ["['+', '15%', 'Magic', 'Resistance']"], "buildto": ["Builds into 1,700 1,950 2,700"], "buildfrom": [], "description": [], "position": []}, "crimson-guard": {"name": 1, "price": "3700", "attr_": ["['+', '250', 'Health', '+', '7', 'HP', 'Regeneration', '+', '2', 'All', 'Attributes', '+', '5', 'Armor']"], "buildto": [], "buildfrom": ["Builds from 800 2,150 750"], "description": ["Active:", "Guard", "For", "12", "seconds,", "grant", "nearby", "allied", "heroes", "and", "buildings", "+2", "armor,", "and", "a", "100%", "chance", "to", "block", "60", "damage", "from", "each", "incoming", "attack.", "Units", "may", "only", "be", "affected", "by", "Guard", "once", "every", "46.0", "seconds.", "Radius:", "1200", "Passive:", "Damage", "Block", "Grants", "a", "50%", "chance", "to", "block", "70", "damage", "from", "incoming", "attacks", "on", "melee", "heroes,", "and", "35", "damage", "on", "ranged.", "46"], "position": []}, "crown": {"name": 1, "price": "450", "attr_": ["['+', '4', 'All', 'Attributes']"], "buildto": ["Builds into 2,700 1,625 2,050 2,750"], "buildfrom": [], "description": [], "position": []}, "crystalys": {"name": 1, "price": "2130", "attr_": ["['+', '38', 'Damage']"], "buildto": ["Builds into 5,330 7,205"], "buildfrom": ["Builds from 430 1,200 500"], "description": ["Passive:", "Critical", "Strike", "Grants", "each", "attack", "a", "20%", "chance", "to", "deal", "175%", "damage."], "position": []}, "daedalus": {"name": 1, "price": "5330", "attr_": ["['+', '80', 'Damage']"], "buildto": [], "buildfrom": ["Builds from 2,200 1,000 2,130"], "description": ["Passive:", "Critical", "Strike", "Grants", "each", "attack", "a", "30%", "chance", "to", "deal", "235%", "damage."], "position": []}, "dagon-level-2": {"name": 1, "price": "3950", "attr_": ["['+', '13', '/', '16', '/', '19', '/', '22', '/', '25', 'Intelligence', '+', '5', 'All', 'Attributes']"], "buildto": ["Builds into 5,200"], "buildfrom": ["Builds from 1,250 2,700"], "description": ["Active:", "Energy", "Burst", "Emits", "a", "powerful", "burst", "of", "magical", "damage", "upon", "a", "targeted", "enemy", "unit.", "Upgradable.", "Damage:", "400", "/", "500", "/", "600", "/", "700", "/", "800", "Range:", "600", "/", "650", "/", "700", "/", "750", "/", "800", "Mana", "Cost:", "140.0", "35", "30", "25", "20", "15", "120", "140", "160", "180", "200"], "position": []}, "dagon-level-3": {"name": 1, "price": "5200", "attr_": ["['+', '13', '/', '16', '/', '19', '/', '22', '/', '25', 'Intelligence', '+', '5', 'All', 'Attributes']"], "buildto": ["Builds into 6,450"], "buildfrom": ["Builds from 1,250 3,950"], "description": ["Active:", "Energy", "Burst", "Emits", "a", "powerful", "burst", "of", "magical", "damage", "upon", "a", "targeted", "enemy", "unit.", "Upgradable.", "Damage:", "400", "/", "500", "/", "600", "/", "700", "/", "800", "Range:", "600", "/", "650", "/", "700", "/", "750", "/", "800", "Mana", "Cost:", "160.0", "35", "30", "25", "20", "15", "120", "140", "160", "180", "200"], "position": []}, "dagon-level-4": {"name": 1, "price": "6450", "attr_": ["['+', '13', '/', '16', '/', '19', '/', '22', '/', '25', 'Intelligence', '+', '5', 'All', 'Attributes']"], "buildto": ["Builds into 7,700"], "buildfrom": ["Builds from 1,250 5,200"], "description": ["Active:", "Energy", "Burst", "Emits", "a", "powerful", "burst", "of", "magical", "damage", "upon", "a", "targeted", "enemy", "unit.", "Upgradable.", "Damage:", "400", "/", "500", "/", "600", "/", "700", "/", "800", "Range:", "600", "/", "650", "/", "700", "/", "750", "/", "800", "Mana", "Cost:", "180.0", "35", "30", "25", "20", "15", "120", "140", "160", "180", "200"], "position": []}, "dagon-level-5": {"name": 1, "price": "7700", "attr_": ["['+', '13', '/', '16', '/', '19', '/', '22', '/', '25', 'Intelligence', '+', '5', 'All', 'Attributes']"], "buildto": [], "buildfrom": ["Builds from 1,250 6,450"], "description": ["Active:", "Energy", "Burst", "Emits", "a", "powerful", "burst", "of", "magical", "damage", "upon", "a", "targeted", "enemy", "unit.", "Damage:", "400", "/", "500", "/", "600", "/", "700", "/", "800", "Range:", "600", "/", "650", "/", "700", "/", "750", "/", "800", "Mana", "Cost:", "200.0", "35", "30", "25", "20", "15", "120", "140", "160", "180", "200"], "position": []}, "dagon": {"name": 1, "price": "2700", "attr_": ["['+', '13', '/', '16', '/', '19', '/', '22', '/', '25', 'Intelligence', '+', '5', 'All', 'Attributes']"], "buildto": ["Builds into 3,950"], "buildfrom": ["Builds from 1,000 1,250 450"], "description": ["Active:", "Energy", "Burst", "Emits", "a", "powerful", "burst", "of", "magical", "damage", "upon", "a", "targeted", "enemy", "unit.", "Upgradable.", "Damage:", "400", "/", "500", "/", "600", "/", "700", "/", "800", "Range:", "600", "/", "650", "/", "700", "/", "750", "/", "800", "Mana", "Cost:", "120.0", "35", "30", "25", "20", "15", "120", "140", "160", "180", "200"], "position": []}, "demon-edge": {"name": 1, "price": "2200", "attr_": ["['+', '42', 'Damage']"], "buildto": ["Builds into 6,000 4,175 5,330 4,400"], "buildfrom": [], "description": [], "position": []}, "desolator": {"name": 1, "price": "3500", "attr_": ["['+', '50', 'Damage']"], "buildto": [], "buildfrom": ["Builds from 1,600 1,600 300"], "description": ["Passive:", "Corruption", "Your", "attacks", "reduce", "the", "target's", "armor", "by", "-7", "for", "15.0", "seconds."], "position": []}, "diffusal-blade": {"name": 1, "price": "3150", "attr_": ["['+', '20', 'Agility', '+', '10', 'Intelligence']"], "buildto": [], "buildfrom": ["Builds from 450 1,000 1,000 700"], "description": ["Active:", "Inhibit", "Targets", "an", "enemy,", "slowing", "it", "for", "4.0", "seconds.", "Range:", "600", "Passive:", "Manabreak", "Each", "attack", "burns", "50", "mana", "from", "the", "target,", "and", "deals", "0.8", "physical", "damage", "per", "burned", "mana.", "Burns", "16", "mana", "per", "attack", "from", "melee", "illusions", "and", "8", "mana", "per", "attack", "from", "ranged", "illusions.", "15"], "position": []}, "divine-rapier": {"name": 1, "price": "6000", "attr_": ["['+', '330', 'Damage']"], "buildto": [], "buildfrom": ["Builds from 2,200 3,800"], "description": ["Passive:", "Everlasting", "Dropped", "on", "death,", "and", "cannot", "be", "destroyed.", "Becomes", "unusable", "if", "picked", "up", "by", "an", "ally", "of", "its", "owner", "until", "it", "is", "returned", "to", "its", "owner.", "It", "is", "immediately", "usable", "by", "anybody", "if", "an", "enemy", "of", "the", "owner", "picks", "it", "up", "and", "is", "killed.", "A", "dropped", "Rapier", "cannot", "be", "picked", "up", "by", "a", "courier."], "position": []}, "dragon-lance": {"name": 1, "price": "1900", "attr_": ["['+', '12', 'Agility', '+', '12', 'Strength']"], "buildto": ["Builds into 4,600"], "buildfrom": ["Builds from 450 450 1,000"], "description": ["Passive:", "Dragon's", "Reach", "Increases", "attack", "range", "of", "ranged", "heroes", "by", "140", "."], "position": []}, "drum-of-endurance": {"name": 1, "price": "1625", "attr_": ["['+', '6', 'Intelligence', '+', '6', 'Strength', '+', '6', 'Agility', '+', '1.25', 'Mana', 'Regeneration', '+', '20', 'Movement', 'Speed']"], "buildto": [], "buildfrom": ["Builds from 325 600 250 450"], "description": ["Active:", "Endurance", "Gives", "+35", "attack", "speed", "and", "+13%", "movement", "speed", "to", "nearby", "allies", "for", "6", "seconds.", "Radius:", "1200", "30"], "position": []}, "dust-of-appearance": {"name": 1, "price": "180", "attr_": [], "buildto": [], "buildfrom": [], "description": ["Use:", "Reveal", "Reveals", "and", "slows", "invisible", "heroes", "by", "-20%", "in", "a", "1050", "radius", "around", "the", "caster", "for", "12", "seconds.", "30"], "position": []}, "eaglesong": {"name": 1, "price": "3200", "attr_": ["['+', '25', 'Agility']"], "buildto": ["Builds into 5,475 4,700"], "buildfrom": [], "description": [], "position": []}, "echo-sabre": {"name": 1, "price": "2650", "attr_": ["['+', '10', 'Intelligence', '+', '12', 'Strength', '+', '10', 'Attack', 'Speed', '+', '12', 'Damage', '+', '1.25', 'Mana', 'Regeneration']"], "buildto": [], "buildfrom": ["Builds from 1,000 1,650"], "description": ["Passive:", "Echo", "Strike", "Causes", "melee", "attacks", "to", "attack", "twice", "in", "quick", "succession.", "The", "double", "attacks", "apply", "a", "100%", "movement", "slow", "for", "0.8", "seconds", "on", "each", "strike.", "5"], "position": []}, "enchanted-mango": {"name": 1, "price": "70", "attr_": ["['+', '0.6', 'HP', 'Regeneration']"], "buildto": [], "buildfrom": [], "description": ["Use:", "Eat", "Mango", "Instantly", "restores", "125", "mana.", "Range:", "400"], "position": []}, "energy-booster": {"name": 1, "price": "900", "attr_": ["['+', '250', 'Mana']"], "buildto": ["Builds into 3,200 1,400 4,000 2,350 3,100 2,700"], "buildfrom": [], "description": [], "position": []}, "ethereal-blade": {"name": 1, "price": "4700", "attr_": ["['+', '40', 'Agility', '+', '10', 'Strength', '+', '10', 'Intelligence']"], "buildto": [], "buildfrom": ["Builds from 1,500 3,200"], "description": ["Active:", "Ether", "Blast", "Converts", "the", "target", "unit", "to", "ethereal", "form,", "rendering", "them", "immune", "to", "physical", "damage,", "but", "unable", "to", "attack", "and", "-40%", "more", "vulnerable", "to", "magic", "damage.", "Lasts", "for", "4.0", "seconds", "on", "allies", "and", "4.0", "seconds", "on", "enemies.", "Enemy", "targets", "are", "also", "slowed", "by", "-80%", ",", "and", "take", "2.0", "x", "your", "primary", "attribute", "+", "75", "as", "magical", "damage.", "Range:", "800", "20", "100"], "position": []}, "euls-scepter-of-divinity": {"name": 1, "price": "2750", "attr_": ["['+', '10', 'Intelligence', '+', '5.0', 'Mana', 'Regeneration', '+', '20', 'Movement', 'Speed']"], "buildto": [], "buildfrom": ["Builds from 1,000 850 650 250"], "description": ["Active:", "Cyclone", "Sweeps", "a", "target", "unit", "up", "into", "a", "cyclone,", "making", "them", "invulnerable", "for", "2.5", "seconds.", "Cyclone", "can", "only", "be", "cast", "on", "enemy", "units", "or", "yourself.", "Enemy", "units", "take", "50", "magical", "damage", "upon", "landing.", "Range:", "575", "Dispel", "Type:", "Basic", "Dispel", "23", "175"], "position": []}, "eye-of-skadi": {"name": 1, "price": "5500", "attr_": ["['+', '25', 'All', 'Attributes', '+', '225', 'Health', '+', '250', 'Mana']"], "buildto": [], "buildfrom": ["Builds from 2,150 2,150 1,200"], "description": ["Passive:", "Cold", "Attack", "Attacks", "lower", "enemy", "movement", "and", "attack", "speed", "for", "3.0", "seconds.", "Slows", "enemy", "ranged", "units", "by", "-45%", "movement", "speed", "and", "by", "-45", "attack", "speed.", "Slows", "enemy", "melee", "units", "by", "-20%", "movement", "speed", "and", "by", "-20", "attack", "speed."], "position": []}, "faerie-fire": {"name": 1, "price": "70", "attr_": ["['+', '2', 'Damage']"], "buildto": [], "buildfrom": [], "description": ["Use:", "Imbue", "Instantly", "restores", "85", "health.", "5"], "position": []}, "force-staff": {"name": 1, "price": "2250", "attr_": ["['+', '10', 'Intelligence', '+', '2.5', 'HP', 'Regeneration']"], "buildto": ["Builds into 4,600"], "buildfrom": ["Builds from 1,000 300 950"], "description": ["Active:", "Force", "Pushes", "any", "target", "unit", "600", "units", "in", "the", "direction", "it", "is", "facing.", "Range:", "750", "23", "100"], "position": []}, "gauntlets-of-strength": {"name": 1, "price": "135", "attr_": ["['+', '3', 'Strength']"], "buildto": ["Builds into 515 770"], "buildfrom": [], "description": [], "position": []}, "gem-of-true-sight": {"name": 1, "price": "900", "attr_": [], "buildto": [], "buildfrom": [], "description": ["Passive:", "True", "Sight", "Grants", "the", "ability", "to", "see", "invisible", "units", "and", "wards", "to", "any", "allied", "vision", "within", "900", "range", "of", "its", "carrier.", "Passive:", "Everlasting", "Dropped", "on", "death,", "and", "cannot", "be", "destroyed."], "position": []}, "ghost-scepter": {"name": 1, "price": "1500", "attr_": ["['+', '5', 'All', 'Attributes']"], "buildto": ["Builds into 4,700"], "buildfrom": [], "description": ["Active:", "Ghost", "Form", "You", "enter", "ghost", "form", "for", "4.0", "seconds,", "becoming", "immune", "to", "physical", "damage,", "but", "are", "unable", "to", "attack", "and", "-40%", "more", "vulnerable", "to", "magic", "damage.", "20"], "position": []}, "glimmer-cape": {"name": 1, "price": "1950", "attr_": ["['+', '20', 'Attack', 'Speed', '+', '15%', 'Magic', 'Resistance']"], "buildto": [], "buildfrom": ["Builds from 550 1,400"], "description": ["Active:", "Glimmer", "After", "a", "0.6", "second", "delay,", "grants", "invisibility", "and", "45%", "magic", "resistance", "to", "you", "or", "a", "target", "allied", "unit", "for", "5.0", "seconds.", "Range:", "800", "Can", "be", "cast", "while", "channelling.", "14", "90"], "position": []}, "gloves-of-haste": {"name": 1, "price": "500", "attr_": ["['+', '20', 'Attack', 'Speed']"], "buildto": ["Builds into 1,450 2,150 2,380 2,175"], "buildfrom": [], "description": [], "position": []}, "guardian-greaves": {"name": 1, "price": "5475", "attr_": ["['+', '17%', 'Movement', 'Speed', '+', '250', 'Mana', '+', '5', 'All', 'Attributes', '+', '5', 'Armor']"], "buildto": [], "buildfrom": ["Builds from 2,275 1,400 1,800"], "description": ["Active:", "Mend", "Restores", "300", "health", "and", "200", "mana", "to", "nearby", "allies,", "and", "removes", "most", "negative", "effects", "from", "the", "caster.", "Radius:", "1200", "Dispel", "Type:", "Basic", "Dispel", "Passive:", "Guardian", "Aura", "Provides", "nearby", "allies", "with", "3.5", "health", "regeneration", "and", "2", "bonus", "armor.", "If", "an", "allied", "hero's", "health", "falls", "below", "20%", ",", "they", "receive", "16", "health", "regeneration", "and", "10", "armor.", "Movement", "speed", "bonuses", "from", "multiple", "pairs", "of", "boots", "do", "not", "stack.", "40"], "position": []}, "hand-of-midas": {"name": 1, "price": "2150", "attr_": ["['+', '40', 'Attack', 'Speed']"], "buildto": [], "buildfrom": ["Builds from 500 1,650"], "description": ["Active:", "Transmute", "Kills", "a", "non-hero", "target", "for", "160", "gold", "and", "1.85", "x", "experience.", "Cannot", "be", "used", "on", "Ancient", "Creeps.", "Range:", "600", "90"], "position": []}, "headdress": {"name": 1, "price": "525", "attr_": ["['+', '2', 'All', 'Attributes']"], "buildto": ["Builds into 2,275 3,025 2,175"], "buildfrom": ["Builds from 50 300 175"], "description": ["Passive:", "Regeneration", "Aura", "Grants", "2.0", "health", "regeneration", "to", "allies.", "Radius:", "1200"], "position": []}, "healing-salve": {"name": 1, "price": "110", "attr_": [], "buildto": [], "buildfrom": [], "description": ["Use:", "Salve", "Grants", "50", "health", "regeneration", "to", "the", "target", "for", "8", "seconds.", "If", "the", "unit", "is", "attacked", "by", "an", "enemy", "hero", "or", "Roshan,", "the", "effect", "is", "lost.", "Range:", "250"], "position": []}, "heart-of-tarrasque": {"name": 1, "price": "5200", "attr_": ["['+', '45', 'Strength', '+', '400', 'Health', '+', '50%', 'Health', 'Regen', 'Amplification']"], "buildto": [], "buildfrom": ["Builds from 3,000 1,100 400 700"], "description": ["Passive:", "Health", "Regeneration", "Restores", "5.0%", "of", "max", "health", "per", "second.", "If", "damage", "is", "taken", "from", "an", "enemy", "hero", "or", "Roshan,", "this", "ability", "is", "disabled", "for", "5", "seconds", "for", "melee", "heroes,", "or", "7", "seconds", "for", "ranged", "heroes.", "7"], "position": []}, "heavens-halberd": {"name": 1, "price": "3450", "attr_": ["['+', '25%', 'Evasion', '+', '25', 'Damage', '+', '20', 'Strength', '+', '14%', 'Status', 'Resistance']"], "buildto": [], "buildfrom": ["Builds from 1,400 2,050"], "description": ["Active:", "Disarm", "Prevents", "a", "target", "from", "attacking", "for", "3.0", "seconds", "on", "melee", "targets,", "and", "5.0", "seconds", "on", "ranged", "targets.", "Range:", "600", "18", "100"], "position": []}, "helm-of-iron-will": {"name": 1, "price": "900", "attr_": ["['+', '5', 'Armor', '+', '3.5', 'HP', 'Regeneration']"], "buildto": ["Builds into 2,380 2,050 4,700"], "buildfrom": [], "description": [], "position": []}, "helm-of-the-dominator": {"name": 1, "price": "2175", "attr_": ["['+', '2', 'All', 'Attributes']"], "buildto": [], "buildfrom": ["Builds from 500 850 525 300"], "description": ["Active:", "Dominate", "Takes", "control", "of", "one", "neutral,", "non-ancient", "target", "unit", "and", "sets", "its", "movement", "speed", "to", "425", "and", "max", "health", "to", "a", "minimum", "of", "1500", ".", "Dominated", "units", "with", "a", "max", "health", "of", "greater", "than", "1500", "retain", "their", "original", "max", "health.", "Dominated", "unit's", "bounty", "is", "set", "to", "200", "gold.", "Range:", "700", "Passive:", "Dominator", "Aura", "Increases", "nearby", "allies'", "attack", "speed", "by", "20", "and", "health", "regen", "by", "8.5", ".", "Radius:", "1200", "60"], "position": []}, "holy-locket": {"name": 1, "price": "2700", "attr_": ["['+', '200', 'Health', '+', '325', 'Mana', '+', '4.0', 'HP', 'Regeneration', '+', '15%', 'Magic', 'Resistance']"], "buildto": [], "buildfrom": ["Builds from 550 900 550 700"], "description": ["Passive:", "Holy", "Blessing", "Amplifies", "heals", "and", "regeneration", "you", "provide", "by", "25%", "."], "position": []}, "hood-of-defiance": {"name": 1, "price": "1700", "attr_": ["['+', '8.0', 'HP', 'Regeneration', '+', '25%', 'Magic', 'Resistance']"], "buildto": ["Builds into 3,025"], "buildfrom": ["Builds from 300 550 850"], "description": ["Active:", "Barrier", "Creates", "a", "spell", "shield", "that", "absorbs", "up", "to", "325", "magical", "damage.", "Lasts", "12", "seconds.", "60", "75"], "position": []}, "hurricane-pike": {"name": 1, "price": "4600", "attr_": ["['+', '13', 'Intelligence', '+', '2.5', 'HP', 'Regeneration', '+', '20', 'Agility', '+', '15', 'Strength']"], "buildto": [], "buildfrom": ["Builds from 2,250 1,900 450"], "description": ["Active:", "Hurricane", "Thrust", "Pushes", "you", "and", "target", "enemy", "450", "units", "away", "from", "each", "other,", "and", "for", "5.0", "seconds,", "allows", "you", "to", "make", "4", "attacks", "against", "the", "target", "without", "range", "restrictions", "and", "with", "+100", "attack", "speed.", "Works", "like", "Force", "Staff", "when", "used", "on", "self", "or", "allies.", "Allied", "Range:", "800", "Enemy", "Range:", "400", "Passive:", "Dragon's", "Reach", "Increases", "attack", "range", "of", "ranged", "heroes", "by", "140", ".", "23", "100"], "position": []}, "hyperstone": {"name": 1, "price": "2000", "attr_": ["['+', '55', 'Attack', 'Speed']"], "buildto": ["Builds into 5,250 5,600 4,000"], "buildfrom": [], "description": [], "position": []}, "infused-raindrops": {"name": 1, "price": "225", "attr_": ["['+', '0.75', 'Mana', 'Regeneration']"], "buildto": ["Builds into 875"], "buildfrom": [], "description": ["Passive:", "Magical", "Damage", "Block", "Consumes", "a", "charge", "to", "block", "120", "magic", "damage", "from", "damage", "instances", "over", "50", "damage.", "Comes", "with", "5", "charges.", "When", "the", "charges", "are", "gone,", "the", "item", "disappears.", "7"], "position": []}, "iron-branch": {"name": 1, "price": "50", "attr_": ["['+', '1', 'All', 'Attributes']"], "buildto": ["Builds into 450 800 525"], "buildfrom": [], "description": ["Use:", "Plant", "Tree", "Targets", "the", "ground", "to", "plant", "a", "happy", "little", "tree", "that", "lasts", "for", "20", "seconds.", "Range:", "400"], "position": []}, "javelin": {"name": 1, "price": "1100", "attr_": [], "buildto": ["Builds into 4,175 2,700"], "buildfrom": [], "description": ["Passive:", "Pierce", "Grants", "each", "attack", "a", "25%", "chance", "to", "pierce", "through", "evasion", "and", "deal", "100", "bonus", "magical", "damage."], "position": []}, "kaya-and-sange": {"name": 1, "price": "4100", "attr_": ["['+', '16', 'Strength', '+', '16', 'Intelligence', '+', '16%', 'Status', 'Resistance', '+', '16%', 'Manacost', 'and', 'Manaloss', 'Reduction', '+', '12%', 'Spell', 'Amplification', '+', '12', 'Damage']"], "buildto": [], "buildfrom": ["Builds from 2,050 2,050"], "description": [], "position": []}, "kaya": {"name": 1, "price": "2050", "attr_": ["['+', '16', 'Intelligence', '+', '12%', 'Manacost', 'and', 'Manaloss', 'Reduction', '+', '8%', 'Spell', 'Amplification']"], "buildto": ["Builds into 4,100 4,100"], "buildfrom": ["Builds from 450 1,000 600"], "description": [], "position": []}, "linkens-sphere": {"name": 1, "price": "5050", "attr_": ["['+', '13', 'All', 'Attributes', '+', '6.5', 'HP', 'Regeneration', '+', '5.0', 'Mana', 'Regeneration']"], "buildto": [], "buildfrom": ["Builds from 2,150 1,700 1,200"], "description": ["Passive:", "Spellblock", "Blocks", "most", "targeted", "spells", "once", "every", "13.0", "seconds.", "Active:", "Transfer", "Spellblock", "Temporarily", "removes", "Spellblock", "from", "the", "item's", "owner", "and", "transfers", "it", "to", "an", "allied", "unit", "for", "13.0", "seconds.", "Range:", "700", "13"], "position": []}, "lotus-orb": {"name": 1, "price": "4000", "attr_": ["['+', '10', 'Armor', '+', '6.5', 'HP', 'Regeneration', '+', '4.0', 'Mana', 'Regeneration', '+', '250', 'Mana']"], "buildto": [], "buildfrom": ["Builds from 1,400 900 1,700"], "description": ["Active:", "Echo", "Shell", "Applies", "a", "shield", "to", "the", "target", "unit", "for", "6.0", "seconds", "which", "re-casts", "most", "targeted", "spells", "back", "to", "their", "caster.", "The", "shielded", "unit", "will", "still", "take", "damage", "from", "the", "spell.", "Range:", "900.0", "Dispel", "Type:", "Basic", "Dispel", "15", "75"], "position": []}, "maelstrom": {"name": 1, "price": "2700", "attr_": ["['+', '24', 'Damage']"], "buildto": ["Builds into 5,600"], "buildfrom": ["Builds from 1,100 1,600"], "description": ["Passive:", "Chain", "Lightning", "Grants", "a", "25%", "chance", "on", "attack", "to", "release", "a", "bolt", "of", "electricity", "that", "leaps", "between", "4", "targets", "within", "a", "900", "radius,", "dealing", "150", "magical", "damage", "to", "each.", "Lightning", "proc", "pierces", "evasion."], "position": []}, "magic-stick": {"name": 1, "price": "200", "attr_": [], "buildto": ["Builds into 450"], "buildfrom": [], "description": ["Active:", "Energy", "Charge", "Instantly", "restores", "15", "health", "and", "mana", "per", "charge", "stored.", "Max", "10", "charges.", "Gains", "a", "charge", "whenever", "a", "visible", "enemy", "within", "1200", "range", "uses", "an", "ability.", "13"], "position": []}, "magic-wand": {"name": 1, "price": "450", "attr_": ["['+', '3', 'All', 'Attributes']"], "buildto": [], "buildfrom": ["Builds from 50 50 200 150"], "description": ["Active:", "Energy", "Charge", "Instantly", "restores", "15", "health", "and", "mana", "per", "charge", "stored.", "Max", "20", "charges.", "Gains", "a", "charge", "whenever", "a", "visible", "enemy", "within", "1200", "range", "uses", "an", "ability.", "13"], "position": []}, "manta-style": {"name": 1, "price": "4700", "attr_": ["['+', '10', 'Strength', '+', '26', 'Agility', '+', '10', 'Intelligence', '+', '12', 'Attack', 'Speed', '+', '20', 'Movement', 'Speed']"], "buildto": [], "buildfrom": ["Builds from 2,150 500 2,050"], "description": ["Active:", "Mirror", "Image", "Creates", "2", "images", "of", "your", "hero", "that", "last", "20", "seconds.", "Melee", "images", "deal", "33%", "damage", "and", "take", "350%", "damage,", "while", "Ranged", "images", "deal", "28%", "and", "take", "400%", "damage.", "Cooldown", "increased", "by", "15.0", "seconds", "on", "ranged", "heroes.", "Dispel", "Type:", "Basic", "Dispel", "45", "125"], "position": []}, "mantle-of-intelligence": {"name": 1, "price": "135", "attr_": ["['+', '3', 'Intelligence']"], "buildto": ["Builds into 515"], "buildfrom": [], "description": [], "position": []}, "mask-of-madness": {"name": 1, "price": "1775", "attr_": ["['+', '10', 'Damage', '+', '10', 'Attack', 'Speed']"], "buildto": [], "buildfrom": ["Builds from 875 900"], "description": ["Active:", "Berserk", "Gives", "110", "attack", "speed", "and", "30", "movement", "speed,", "but", "reduces", "your", "armor", "by", "8", "and", "silences", "you.", "Lasts", "8.0", "seconds.", "Passive:", "Lifesteal", "Heals", "the", "attacker", "for", "20%", "of", "attack", "damage", "dealt.", "22", "25"], "position": []}, "medallion-of-courage": {"name": 1, "price": "1175", "attr_": ["['+', '7', 'Armor', '+', '0.75', 'Mana', 'Regeneration']"], "buildto": ["Builds into 3,875"], "buildfrom": ["Builds from 550 325 300"], "description": ["Active:", "Valor", "If", "cast", "on", "an", "ally,", "grants", "them", "the", "7", "armor,", "and", "removing", "it", "from", "the", "caster.", "If", "cast", "on", "an", "enemy,", "reduces", "7", "armor", "on", "both", "the", "enemy", "and", "the", "caster.", "Cannot", "target", "magic", "immune", "enemies.", "Range:", "1000", "7"], "position": []}, "mekansm": {"name": 1, "price": "2275", "attr_": ["['+', '5', 'All', 'Attributes', '+', '5', 'Armor']"], "buildto": ["Builds into 5,475"], "buildfrom": ["Builds from 950 800 525"], "description": ["Active:", "Restore", "Heals", "275", "health", "and", "gives", "+2", "armor", "to", "allied", "units", "in", "a", "1200", "radius.", "Passive:", "Mekansm", "Aura", "Grants", "3.5", "health", "regeneration", "to", "allied", "units", "in", "a", "1200", "radius.", "65", "225"], "position": []}, "meteor-hammer": {"name": 1, "price": "2625", "attr_": ["['+', '12', 'Strength', '+', '12', 'Intelligence', '+', '5.0', 'HP', 'Regeneration', '+', '3.0', 'Mana', 'Regeneration']"], "buildto": [], "buildfrom": ["Builds from 1,000 1,000 300 325"], "description": ["Active:", "Meteor", "Hammer", "CHANNELED", "-", "After", "a", "successful", "channel,", "summons", "a", "meteor", "that", "strikes", "a", "315", "AoE,", "stunning", "enemies", "for", "2.0", "seconds", "and", "dealing", "impact", "damage.", "Continues", "to", "deal", "damage", "over", "time", "to", "enemies", "units", "and", "buildings", "for", "6", "seconds.", "Building", "Impact", "Damage:", "75", "Building", "Over", "Time", "Damage:", "50", "Non-Building", "Impact", "Damage:", "150", "Non-Building", "Over", "Time", "Damage:", "90", "Channel", "Duration:", "2.5", "seconds.", "Landing", "Time:", "0.5", "seconds.", "28", "125"], "position": []}, "mithril-hammer": {"name": 1, "price": "1600", "attr_": ["['+', '24', 'Damage']"], "buildto": ["Builds into 4,050 2,950 2,700 3,500"], "buildfrom": [], "description": [], "position": []}, "mjollnir": {"name": 1, "price": "5600", "attr_": ["['+', '24', 'Damage', '+', '75', 'Attack', 'Speed']"], "buildto": [], "buildfrom": ["Builds from 2,000 900 2,700"], "description": ["Active:", "Static", "Charge", "Places", "a", "charged", "shield", "on", "a", "target", "unit", "for", "15.0", "seconds", "which", "has", "a", "20%", "chance", "to", "release", "a", "200", "magical", "damage", "shocking", "bolt", "at", "a", "nearby", "attacker", "and", "4", "additional", "enemies.", "Range:", "800", "Passive:", "Chain", "Lightning", "Grants", "a", "25%", "chance", "on", "attack", "to", "release", "a", "bolt", "of", "electricity", "that", "leaps", "between", "12", "targets", "within", "a", "900", "radius,", "dealing", "170", "magical", "damage", "to", "each.", "Lightning", "proc", "pierces", "evasion.", "35", "50"], "position": []}, "monkey-king-bar": {"name": 1, "price": "4175", "attr_": ["['+', '52', 'Damage', '+', '10', 'Attack', 'Speed']"], "buildto": [], "buildfrom": ["Builds from 1,100 875 2,200"], "description": ["Passive:", "Pierce", "Grants", "each", "attack", "a", "75%", "chance", "to", "pierce", "through", "evasion", "and", "deal", "100", "bonus", "magical", "damage."], "position": []}, "moon-shard": {"name": 1, "price": "4000", "attr_": ["['+', '140', 'Attack', 'Speed']"], "buildto": [], "buildfrom": ["Builds from 2,000 2,000"], "description": ["Use:", "Consume", "Consume", "the", "Moon", "Shard", "to", "permanently", "gain", "60", "attack", "speed", "and", "200", "bonus", "night", "vision.", "Max", "1", "use.", "Passive:", "Shade", "Sight", "Grants", "400", "bonus", "night", "vision."], "position": []}, "morbid-mask": {"name": 1, "price": "900", "attr_": [], "buildto": ["Builds into 1,925 5,300 1,775"], "buildfrom": [], "description": ["Passive:", "Lifesteal", "Heals", "the", "attacker", "for", "15%", "of", "attack", "damage", "dealt."], "position": []}, "mystic-staff": {"name": 1, "price": "2700", "attr_": ["['+', '25', 'Intelligence']"], "buildto": ["Builds into 5,700 4,750 5,900"], "buildfrom": [], "description": [], "position": []}, "necronomicon-level-2": {"name": 1, "price": "3700", "attr_": ["['+', '10', '/', '15', '/', '20', 'Strength', '+', '2.0', '/', '2.5', '/', '3.0', 'Mana', 'Regeneration']"], "buildto": ["Builds into 5,000"], "buildfrom": ["Builds from 1,300 2,400"], "description": ["Active:", "Demonic", "Summoning", "Summons", "a", "Warrior", "and", "an", "Archer", "to", "fight", "for", "you", "for", "60", "seconds.", "Warrior:", "Burns", "mana", "every", "hit,", "and", "deals", "magical", "damage", "to", "whoever", "kills", "it.", "Gains", "True", "Sight", "at", "level", "3", ".", "Health:", "700", "/", "800", "/", "900", "Damage:", "75", "/", "100", "/", "125", "Mana", "Break", "Damage:", "30", "/", "40", "/", "50", "Last", "Will", "Damage:", "600", "/", "700", "/", "800", "Archer:", "Has", "a", "passive", "movement", "and", "attack", "speed", "aura.", "Gains", "Purge", "at", "Level", "3", ".", "Health:", "700", "/", "800", "/", "900", "Damage:", "60", "/", "90", "/", "120", "Aura", "Move", "Speed:", "5", "/", "7", "/", "9", "Aura", "Attack", "Speed:", "5", "/", "10", "/", "15", "Aura", "Radius:", "1200", "90", "50"], "position": []}, "necronomicon-level-3": {"name": 1, "price": "5000", "attr_": ["['+', '10', '/', '15', '/', '20', 'Strength', '+', '2.0', '/', '2.5', '/', '3.0', 'Mana', 'Regeneration']"], "buildto": [], "buildfrom": ["Builds from 1,300 3,700"], "description": ["Active:", "Demonic", "Summoning", "Summons", "a", "Warrior", "and", "an", "Archer", "to", "fight", "for", "you", "for", "60", "seconds.", "Warrior:", "Burns", "mana", "every", "hit,", "and", "deals", "magical", "damage", "to", "whoever", "kills", "it.", "Gains", "True", "Sight", "at", "level", "3", ".", "Health:", "700", "/", "800", "/", "900", "Damage:", "75", "/", "100", "/", "125", "Mana", "Break", "Damage:", "30", "/", "40", "/", "50", "Last", "Will", "Damage:", "600", "/", "700", "/", "800", "Archer:", "Has", "a", "passive", "movement", "and", "attack", "speed", "aura.", "Gains", "Purge", "at", "Level", "3", ".", "Health:", "700", "/", "800", "/", "900", "Damage:", "60", "/", "90", "/", "120", "Aura", "Move", "Speed:", "5", "/", "7", "/", "9", "Aura", "Attack", "Speed:", "5", "/", "10", "/", "15", "Aura", "Radius:", "1200", "90", "50"], "position": []}, "necronomicon": {"name": 1, "price": "2400", "attr_": ["['+', '10', '/', '15', '/', '20', 'Strength', '+', '2.0', '/', '2.5', '/', '3.0', 'Mana', 'Regeneration']"], "buildto": ["Builds into 3,700"], "buildfrom": ["Builds from 450 325 325 1,300"], "description": ["Active:", "Demonic", "Summoning", "Summons", "a", "Warrior", "and", "an", "Archer", "to", "fight", "for", "you", "for", "60", "seconds.", "Warrior:", "Burns", "mana", "every", "hit,", "and", "deals", "magical", "damage", "to", "whoever", "kills", "it.", "Gains", "True", "Sight", "at", "level", "3", ".", "Health:", "700", "/", "800", "/", "900", "Damage:", "75", "/", "100", "/", "125", "Mana", "Break", "Damage:", "30", "/", "40", "/", "50", "Last", "Will", "Damage:", "600", "/", "700", "/", "800", "Archer:", "Has", "a", "passive", "movement", "and", "attack", "speed", "aura.", "Gains", "Purge", "at", "Level", "3", ".", "Health:", "700", "/", "800", "/", "900", "Damage:", "60", "/", "90", "/", "120", "Aura", "Move", "Speed:", "5", "/", "7", "/", "9", "Aura", "Attack", "Speed:", "5", "/", "7", "/", "9", "Aura", "Radius:", "1200", "90", "50"], "position": []}, "null-talisman": {"name": 1, "price": "515", "attr_": ["['+', '3', 'Strength', '+', '3', 'Agility', '+', '6', 'Intelligence', '+', '3%', 'Spell', 'Amplification']"], "buildto": [], "buildfrom": ["Builds from 135 165 215"], "description": [], "position": []}, "nullifier": {"name": 1, "price": "4700", "attr_": ["['+', '65', 'Damage', '+', '5', 'Armor', '+', '6', 'HP', 'Regeneration']"], "buildto": [], "buildfrom": ["Builds from 900 3,800"], "description": ["Active:", "Nullify", "Dispels", "the", "target", "and", "mutes", "them", "for", "6.0", "seconds.", "Anytime", "the", "muted", "target", "is", "attacked,", "it", "will", "be", "slowed", "by", "100%", "for", "0.4", "seconds.", "Dispel", "Type:", "Basic", "Dispel", "13", "75"], "position": []}, "oblivion-staff": {"name": 1, "price": "1650", "attr_": ["['+', '10', 'Intelligence', '+', '10', 'Attack', 'Speed', '+', '10', 'Damage', '+', '1.25', 'Mana', 'Regeneration']"], "buildto": ["Builds into 4,075 2,650"], "buildfrom": ["Builds from 875 450 325"], "description": [], "position": []}, "observer-and-sentry-wards": {"name": 1, "price": "125", "attr_": ["['OBSERVER', 'VISION', 'RANGE:', '1600', 'OBSERVER', 'DURATION', '(MINUTES):', '6', 'SENTRY', 'TRUE', 'SIGHT', 'RANGE:', '1000', 'SENTRY', 'DURATION', '(MINUTES):', '6']"], "buildto": [], "buildfrom": ["Builds from 50 75"], "description": ["Use:", "Plant", "Plant", "the", "currently", "active", "ward.", "Double-Click", "to", "switch", "the", "currently", "active", "ward.", "Range:", "500"], "position": []}, "observer-ward": {"name": 1, "price": "50", "attr_": [], "buildto": ["Builds into 125"], "buildfrom": [], "description": ["Use:", "Plant", "Plants", "an", "Observer", "Ward,", "an", "invisible", "watcher", "that", "gives", "ground", "vision", "in", "a", "1600", "radius", "to", "your", "team.", "Lasts", "6", "minutes.", "Hold", "Control", "to", "give", "one", "Observer", "Ward", "to", "an", "allied", "hero.", "Range:", "500", "1"], "position": []}, "octarine-core": {"name": 1, "price": "5900", "attr_": ["['+', '25', 'Intelligence', '+', '425', 'Health', '+', '425', 'Mana']"], "buildto": [], "buildfrom": ["Builds from 2,700 3,200"], "description": ["Passive:", "Cooldown", "Reduction", "Reduces", "the", "cooldown", "time", "of", "all", "spells", "and", "items", "by", "25%", ".", "Passive:", "Spell", "Lifesteal", "25.0%", "of", "spell", "damage", "dealt", "to", "enemy", "heroes", "is", "returned", "to", "the", "caster", "as", "health,", "regardless", "of", "spell", "damage", "type.", "Lifesteal", "reduced", "to", "5.0%", "against", "creeps."], "position": []}, "ogre-axe": {"name": 1, "price": "1000", "attr_": ["['+', '10', 'Strength']"], "buildto": ["Builds into 4,200 4,050 2,050 2,625 1,900 2,650"], "buildfrom": [], "description": [], "position": []}, "orb-of-venom": {"name": 1, "price": "275", "attr_": [], "buildto": [], "buildfrom": [], "description": ["Passive:", "Poison", "Attack", "Poisons", "the", "target,", "dealing", "5.0", "magical", "damage", "per", "second", "and", "slowing", "movement", "by", "-12%", "if", "the", "equipped", "hero", "is", "melee,", "or", "3.0", "magical", "damage", "per", "second", "and", "slowing", "movement", "by", "-4%", "if", "they", "are", "ranged.", "Lasts", "for", "3.0", "seconds."], "position": []}, "orchid-malevolence": {"name": 1, "price": "4075", "attr_": ["['+', '25', 'Intelligence', '+', '30', 'Attack', 'Speed', '+', '30', 'Damage', '+', '5.5', 'Mana', 'Regeneration']"], "buildto": ["Builds into 7,205"], "buildfrom": ["Builds from 1,650 1,650 775"], "description": ["Active:", "Soul", "Burn", "Silences", "the", "target", "unit", "for", "5.0", "seconds.", "At", "the", "end", "of", "the", "silence,", "30.0%", "of", "the", "damage", "received", "while", "silenced", "is", "inflicted", "as", "bonus", "magical", "damage.", "Range:", "900", "18", "100"], "position": []}, "perseverance": {"name": 1, "price": "1700", "attr_": ["['+', '6.0', 'HP', 'Regeneration', '+', '2.0', 'Mana', 'Regeneration']"], "buildto": ["Builds into 5,100 4,900 5,050 4,400 4,000"], "buildfrom": ["Builds from 850 850"], "description": [], "position": []}, "phase-boots": {"name": 1, "price": "1480", "attr_": ["['+', '15%', 'Movement', 'Speed', '+', '18', 'Damage', '(MELEE)', '+', '12', 'Damage', '(RANGED)', '+', '6', 'Armor']"], "buildto": [], "buildfrom": ["Builds from 430 550 500"], "description": ["Active:", "Phase", "Gives", "22%", "increased", "movement", "speed", "on", "melee", "heroes,", "and", "10%", "on", "ranged", "heroes,", "and", "lets", "you", "move", "through", "units", "and", "turn", "more", "quickly", "for", "3.0", "seconds.", "Movement", "speed", "bonuses", "from", "multiple", "pairs", "of", "boots", "do", "not", "stack.", "8"], "position": []}, "pipe-of-insight": {"name": 1, "price": "3025", "attr_": ["['+', '8.0', 'HP', 'Regeneration', '+', '30%', 'Magic', 'Resistance', '+', '2', 'All', 'Attributes']"], "buildto": [], "buildfrom": ["Builds from 800 525 1,700"], "description": ["Active:", "Barrier", "Gives", "a", "shield", "that", "blocks", "400", "magic", "damage", "to", "all", "nearby", "allies.", "Lasts", "12", "seconds.", "Radius:", "1200", "Passive:", "Insight", "Aura", "Gives", "allied", "units", "2", "health", "regeneration", "and", "10%", "magic", "resistance.", "Radius:", "1200", "60", "100"], "position": []}, "platemail": {"name": 1, "price": "1400", "attr_": ["['+', '10', 'Armor']"], "buildto": ["Builds into 5,250 4,750 4,000"], "buildfrom": [], "description": [], "position": []}, "point-booster": {"name": 1, "price": "1200", "attr_": ["['+', '175', 'Mana', '+', '175', 'Health']"], "buildto": ["Builds into 4,200 3,200 5,500"], "buildfrom": [], "description": [], "position": []}, "power-treads": {"name": 1, "price": "1450", "attr_": ["['+', '15%', 'Movement', 'Speed', '+', '10', 'Selected', 'Attribute', '+', '20', 'Attack', 'Speed']"], "buildto": [], "buildfrom": ["Builds from 450 500 500"], "description": ["Active:", "Switch", "Attribute", "Switches", "between", "+10", "Strength,", "+10", "Agility,", "or", "+10", "Intelligence.", "Movement", "speed", "bonuses", "from", "multiple", "pairs", "of", "boots", "do", "not", "stack."], "position": []}, "quarterstaff": {"name": 1, "price": "875", "attr_": ["['+', '10', 'Damage', '+', '10', 'Attack', 'Speed']"], "buildto": ["Builds into 1,650 4,175 5,475 1,775"], "buildfrom": [], "description": [], "position": []}, "quelling-blade": {"name": 1, "price": "200", "attr_": [], "buildto": ["Builds into 4,400"], "buildfrom": [], "description": ["Active:", "Chop", "Tree/Ward", "Destroy", "a", "target", "tree", "or", "ward.", "Chop", "cast", "range", "is", "increased", "when", "targeting", "wards.", "Tree", "Range:", "350", "Ward", "Range:", "450", "Passive:", "Quell", "Increases", "attack", "damage", "against", "non-hero", "units", "by", "24", "for", "melee", "heroes,", "and", "7", "for", "ranged.", "4"], "position": []}, "radiance": {"name": 1, "price": "5150", "attr_": ["['+', '65', 'Damage']"], "buildto": [], "buildfrom": ["Builds from 3,800 1,350"], "description": ["Toggle:", "Burn", "When", "active,", "scorches", "enemies", "for", "60", "magical", "damage", "per", "second,", "and", "causes", "them", "to", "miss", "17%", "of", "their", "attacks.", "Illusions", "deal", "35", "magical", "damage", "per", "second.", "Radius:", "700"], "position": []}, "reaver": {"name": 1, "price": "3000", "attr_": ["['+', '25', 'Strength']"], "buildto": ["Builds into 5,200 5,300"], "buildfrom": [], "description": [], "position": []}, "recipe-aeon-disk": {"name": 1, "price": "1100", "attr_": [], "buildto": [], "buildfrom": ["Builds from 900 1,100"], "description": [], "position": []}, "recipe-aether-lens": {"name": 1, "price": "600", "attr_": [], "buildto": [], "buildfrom": ["Builds from 850 900"], "description": [], "position": []}, "recipe-aghanims-blessing-2": {"name": 1, "price": "1800", "attr_": [], "buildto": [], "buildfrom": ["Builds from 4,200"], "description": [], "position": []}, "recipe-armlet-of-mordiggian": {"name": 1, "price": "550", "attr_": [], "buildto": [], "buildfrom": ["Builds from 430 900 500"], "description": [], "position": []}, "recipe-assault-cuirass": {"name": 1, "price": "1300", "attr_": [], "buildto": [], "buildfrom": ["Builds from 550 1,400 2,000"], "description": [], "position": []}, "recipe-battle-fury": {"name": 1, "price": "300", "attr_": [], "buildto": [], "buildfrom": ["Builds from 200 2,200 1,700"], "description": [], "position": []}, "recipe-black-king-bar": {"name": 1, "price": "1450", "attr_": [], "buildto": [], "buildfrom": ["Builds from 1,600 1,000"], "description": [], "position": []}, "recipe-bloodthorn": {"name": 1, "price": "1000", "attr_": [], "buildto": [], "buildfrom": ["Builds from 4,075 2,130"], "description": [], "position": []}, "recipe-boots-of-travel": {"name": 1, "price": "2000", "attr_": [], "buildto": ["Builds into 4,500"], "buildfrom": ["Builds from 500"], "description": [], "position": []}, "recipe-bracer": {"name": 1, "price": "215", "attr_": [], "buildto": [], "buildfrom": ["Builds from 135 165"], "description": [], "position": []}, "recipe-buckler": {"name": 1, "price": "200", "attr_": [], "buildto": [], "buildfrom": ["Builds from 550 50"], "description": [], "position": []}, "recipe-crimson-guard": {"name": 1, "price": "750", "attr_": [], "buildto": [], "buildfrom": ["Builds from 800 2,150"], "description": [], "position": []}, "recipe-crystalys": {"name": 1, "price": "500", "attr_": [], "buildto": [], "buildfrom": ["Builds from 430 1,200"], "description": [], "position": []}, "recipe-daedalus": {"name": 1, "price": "1000", "attr_": [], "buildto": [], "buildfrom": ["Builds from 2,200 2,130"], "description": [], "position": []}, "recipe-dagon": {"name": 1, "price": "1250", "attr_": [], "buildto": ["Builds into 3,950 5,200 6,450 7,700"], "buildfrom": ["Builds from 1,000 450"], "description": [], "position": []}, "recipe-diffusal-blade": {"name": 1, "price": "700", "attr_": [], "buildto": [], "buildfrom": ["Builds from 450 1,000 1,000"], "description": [], "position": []}, "recipe-euls-scepter-of-divinity": {"name": 1, "price": "650", "attr_": [], "buildto": [], "buildfrom": ["Builds from 1,000 850 250"], "description": [], "position": []}, "recipe-force-staff": {"name": 1, "price": "950", "attr_": [], "buildto": [], "buildfrom": ["Builds from 1,000 300"], "description": [], "position": []}, "recipe-guardian-greaves": {"name": 1, "price": "1800", "attr_": [], "buildto": [], "buildfrom": ["Builds from 2,275 1,400"], "description": [], "position": []}, "recipe-hand-of-midas": {"name": 1, "price": "1650", "attr_": [], "buildto": [], "buildfrom": ["Builds from 500"], "description": [], "position": []}, "recipe-headdress": {"name": 1, "price": "175", "attr_": [], "buildto": [], "buildfrom": ["Builds from 50 300"], "description": [], "position": []}, "recipe-heart-of-tarrasque": {"name": 1, "price": "400", "attr_": [], "buildto": [], "buildfrom": ["Builds from 3,000 1,100 700"], "description": [], "position": []}, "recipe-helm-of-the-dominator": {"name": 1, "price": "300", "attr_": [], "buildto": [], "buildfrom": ["Builds from 500 850 525"], "description": [], "position": []}, "recipe-holy-locket": {"name": 1, "price": "550", "attr_": [], "buildto": [], "buildfrom": ["Builds from 550 900 700"], "description": [], "position": []}, "recipe-kaya": {"name": 1, "price": "600", "attr_": [], "buildto": [], "buildfrom": ["Builds from 450 1,000"], "description": [], "position": []}, "recipe-linkens-sphere": {"name": 1, "price": "1200", "attr_": [], "buildto": [], "buildfrom": ["Builds from 2,150 1,700"], "description": [], "position": []}, "recipe-magic-wand": {"name": 1, "price": "150", "attr_": [], "buildto": [], "buildfrom": ["Builds from 50 50 200"], "description": [], "position": []}, "recipe-manta-style": {"name": 1, "price": "500", "attr_": [], "buildto": [], "buildfrom": ["Builds from 2,150 2,050"], "description": [], "position": []}, "recipe-mekansm": {"name": 1, "price": "950", "attr_": [], "buildto": [], "buildfrom": ["Builds from 800 525"], "description": [], "position": []}, "recipe-mjollnir": {"name": 1, "price": "900", "attr_": [], "buildto": [], "buildfrom": ["Builds from 2,000 2,700"], "description": [], "position": []}, "recipe-necronomicon": {"name": 1, "price": "1300", "attr_": [], "buildto": ["Builds into 3,700 5,000"], "buildfrom": ["Builds from 450 325 325"], "description": [], "position": []}, "recipe-null-talisman": {"name": 1, "price": "215", "attr_": [], "buildto": [], "buildfrom": ["Builds from 135 165"], "description": [], "position": []}, "recipe-orchid-malevolence": {"name": 1, "price": "775", "attr_": [], "buildto": [], "buildfrom": ["Builds from 1,650 1,650"], "description": [], "position": []}, "recipe-pipe-of-insight": {"name": 1, "price": "800", "attr_": [], "buildto": [], "buildfrom": ["Builds from 525 1,700"], "description": [], "position": []}, "recipe-radiance": {"name": 1, "price": "1350", "attr_": [], "buildto": [], "buildfrom": ["Builds from 3,800"], "description": [], "position": []}, "recipe-refresher-orb": {"name": 1, "price": "1700", "attr_": [], "buildto": [], "buildfrom": ["Builds from 1,700 1,700"], "description": [], "position": []}, "recipe-rod-of-atos": {"name": 1, "price": "850", "attr_": [], "buildto": [], "buildfrom": ["Builds from 1,000 450 450"], "description": [], "position": []}, "recipe-sange": {"name": 1, "price": "600", "attr_": [], "buildto": [], "buildfrom": ["Builds from 450 1,000"], "description": [], "position": []}, "recipe-shivas-guard": {"name": 1, "price": "650", "attr_": [], "buildto": [], "buildfrom": ["Builds from 1,400 2,700"], "description": [], "position": []}, "recipe-silver-edge": {"name": 1, "price": "600", "attr_": [], "buildto": [], "buildfrom": ["Builds from 2,150 2,800"], "description": [], "position": []}, "recipe-solar-crest": {"name": 1, "price": "300", "attr_": [], "buildto": [], "buildfrom": ["Builds from 2,150 1,175 250"], "description": [], "position": []}, "recipe-soul-ring": {"name": 1, "price": "200", "attr_": [], "buildto": [], "buildfrom": ["Builds from 135 135 300"], "description": [], "position": []}, "recipe-spirit-vessel": {"name": 1, "price": "750", "attr_": [], "buildto": [], "buildfrom": ["Builds from 1,100 875 250"], "description": [], "position": []}, "recipe-urn-of-shadows": {"name": 1, "price": "310", "attr_": [], "buildto": [], "buildfrom": ["Builds from 175 165 225"], "description": [], "position": []}, "recipe-veil-of-discord": {"name": 1, "price": "700", "attr_": [], "buildto": [], "buildfrom": ["Builds from 900 450"], "description": [], "position": []}, "recipe-vladmirs-offering": {"name": 1, "price": "525", "attr_": [], "buildto": [], "buildfrom": ["Builds from 900 500"], "description": [], "position": []}, "recipe-yasha": {"name": 1, "price": "600", "attr_": [], "buildto": [], "buildfrom": ["Builds from 450 1,000"], "description": [], "position": []}, "refresher-orb": {"name": 1, "price": "5100", "attr_": ["['+', '13', 'HP', 'Regeneration', '+', '12.0', 'Mana', 'Regeneration']"], "buildto": [], "buildfrom": ["Builds from 1,700 1,700 1,700"], "description": ["Active:", "Reset", "Cooldowns", "Resets", "the", "cooldowns", "of", "all", "your", "items", "and", "abilities.", "195", "375"], "position": []}, "refresher-shard": {"name": 1, "price": "1000", "attr_": [], "buildto": [], "buildfrom": [], "description": ["Use:", "Reset", "Cooldowns", "Resets", "the", "cooldowns", "of", "all", "your", "items", "and", "abilities.", "200"], "position": []}, "ring-of-basilius": {"name": 1, "price": "500", "attr_": ["['+', '8', 'Damage']"], "buildto": ["Builds into 1,925"], "buildfrom": ["Builds from 175 325"], "description": ["Passive:", "Basilius", "Aura", "Grants", "0.75", "mana", "regeneration", "and", "2", "armor", "in", "a", "1200", "radius.", "Toggle:", "Aura", "Deactivate", "aura", "to", "stop", "affecting", "non-hero", "units."], "position": []}, "ring-of-health": {"name": 1, "price": "850", "attr_": ["['+', '6.0', 'HP', 'Regeneration']"], "buildto": ["Builds into 1,700 2,150 1,700 2,175"], "buildfrom": [], "description": [], "position": []}, "ring-of-protection": {"name": 1, "price": "175", "attr_": ["['+', '2.0', 'Armor']"], "buildto": ["Builds into 500 875"], "buildfrom": [], "description": [], "position": []}, "ring-of-regen": {"name": 1, "price": "300", "attr_": ["['+', '2.0', 'HP', 'Regeneration']"], "buildto": ["Builds into 525 2,250 1,700 770 1,050 2,625"], "buildfrom": [], "description": [], "position": []}, "ring-of-tarrasque": {"name": 1, "price": "700", "attr_": ["['+', '150', 'Health', '+', '3.75', 'HP', 'Regeneration']"], "buildto": ["Builds into 5,200 2,700"], "buildfrom": [], "description": [], "position": []}, "river-vial-blood": {"name": 1, "price": [], "attr_": [], "buildto": [], "buildfrom": [], "description": [], "position": []}, "river-vial-dry": {"name": 1, "price": [], "attr_": [], "buildto": [], "buildfrom": [], "description": ["Pour", "this", "serum", "into", "the", "river", "to", "dry", "up", "the", "water", "for", "15", "minutes.", "Using", "this", "item", "on", "the", "river", "will", "permanently", "consume", "one", "charge", "from", "your", "Armory", "supply", "upon", "expiration", "of", "the", "effect", ".", "Charges", "do", "not", "get", "consumed", "if", "the", "effect", "is", "replaced", "by", "a", "stronger", "vial", "before", "expiration.", "Vials", "can", "only", "be", "used", "if", "at", "least", "one", "charge", "remains", "in", "your", "Armory.", "Charges", "will", "only", "be", "used", "by", "successfully", "enchanting", "the", "river,", "and", "will", "not", "be", "consumed", "if", "the", "item", "is", "sold,", "dropped,", "or", "destroyed", "during", "a", "game.", "You", "can", "only", "cast", "a", "vial", "on", "the", "river", "if", "there's", "not", "a", "stronger", "vial", "already", "in", "effect."], "position": []}, "river-vial-potion": {"name": 1, "price": [], "attr_": [], "buildto": [], "buildfrom": [], "description": ["Pour", "this", "serum", "into", "the", "river", "to", "transform", "the", "water", "into", "a", "purple", "bubbling", "potion", "for", "15", "minutes.", "Using", "this", "item", "on", "the", "river", "will", "permanently", "consume", "one", "charge", "from", "your", "Armory", "supply", "upon", "expiration", "of", "the", "effect.", "Charges", "do", "not", "get", "consumed", "if", "the", "effect", "is", "replaced", "by", "a", "stronger", "vial", "before", "expiration.", "Vials", "can", "only", "be", "used", "if", "at", "least", "one", "charge", "remains", "in", "your", "Armory.", "Charges", "will", "only", "be", "used", "by", "successfully", "enchanting", "the", "river,", "and", "will", "not", "be", "consumed", "if", "the", "item", "is", "sold,", "dropped,", "or", "destroyed", "during", "a", "game.", "You", "can", "only", "cast", "a", "vial", "on", "the", "river", "if", "there's", "not", "a", "stronger", "vial", "already", "in", "effect."], "position": []}, "river-vial-slime": {"name": 1, "price": [], "attr_": ["['+', '2', 'Damage']"], "buildto": [], "buildfrom": [], "description": ["Use:", "Imbue", "Instantly", "restores", "85", "health.", "5"], "position": []}, "robe-of-the-magi": {"name": 1, "price": "450", "attr_": ["['+', '6', 'Intelligence']"], "buildto": ["Builds into 1,650 2,200 3,150 2,050"], "buildfrom": [], "description": [], "position": []}, "rod-of-atos": {"name": 1, "price": "2750", "attr_": ["['+', '20', 'Intelligence', '+', '10', 'Strength', '+', '10', 'Agility']"], "buildto": [], "buildfrom": ["Builds from 1,000 850 450 450"], "description": ["Active:", "Cripple", "Roots", "the", "target", "for", "2.0", "seconds.", "Range:", "1100", "18", "50"], "position": []}, "sacred-relic": {"name": 1, "price": "3800", "attr_": ["['+', '60', 'Damage']"], "buildto": ["Builds into 6,000 5,150 4,700"], "buildfrom": [], "description": [], "position": []}, "sages-mask": {"name": 1, "price": "325", "attr_": ["['+', '0.75', 'Mana', 'Regeneration']"], "buildto": ["Builds into 1,650 500 2,400 1,625 1,175 2,625"], "buildfrom": [], "description": [], "position": []}, "sange-and-yasha": {"name": 1, "price": "4100", "attr_": ["['+', '16', 'Strength', '+', '16', 'Agility', '+', '16%', 'Status', 'Resistance', '+', '16', 'Attack', 'Speed', '+', '30', 'Movement', 'Speed', '+', '12', 'Damage']"], "buildto": [], "buildfrom": ["Builds from 2,050 2,050"], "description": [], "position": []}, "sange": {"name": 1, "price": "2050", "attr_": ["['+', '16', 'Strength', '+', '12%', 'Status', 'Resistance', '+', '8', 'Damage']"], "buildto": ["Builds into 4,100 3,450 4,100"], "buildfrom": ["Builds from 450 1,000 600"], "description": [], "position": []}, "satanic": {"name": 1, "price": "5300", "attr_": ["['+', '25', 'Strength', '+', '25', 'Damage', '+', '30%', 'Status', 'Resistance']"], "buildto": [], "buildfrom": ["Builds from 1,400 900 3,000"], "description": ["Active:", "Unholy", "Rage", "Increases", "Lifesteal", "percentage", "to", "200%", "for", "5.0", "seconds.", "Passive:", "Lifesteal", "Heals", "the", "attacker", "for", "25%", "of", "attack", "damage", "dealt.", "35"], "position": []}, "scythe-of-vyse": {"name": 1, "price": "5700", "attr_": ["['+', '10', 'Strength', '+', '10', 'Agility', '+', '35', 'Intelligence', '+', '9.0', 'Mana', 'Regeneration']"], "buildto": [], "buildfrom": ["Builds from 2,150 850 2,700"], "description": ["Active:", "Hex", "Turns", "a", "target", "unit", "into", "a", "harmless", "critter", "for", "3.5", "seconds.", "The", "target", "has", "a", "base", "movement", "speed", "of", "140", "and", "will", "be", "silenced,", "muted,", "and", "disarmed.", "Instantly", "destroys", "illusions.", "Range:", "800", "22", "250"], "position": []}, "sentry-ward": {"name": 1, "price": "75", "attr_": [], "buildto": ["Builds into 125"], "buildfrom": [], "description": ["Use:", "Plant", "Plants", "a", "Sentry", "Ward,", "an", "invisible", "watcher", "that", "grants", "True", "Sight,", "the", "ability", "to", "see", "invisible", "enemy", "units", "and", "wards,", "to", "any", "existing", "allied", "vision", "within", "a", "1000", "radius.", "Lasts", "6", "minutes.", "Does", "not", "grant", "ground", "vision.", "Hold", "Control", "to", "give", "one", "Sentry", "Ward", "to", "an", "allied", "hero.", "Range:", "500", "1"], "position": []}, "shadow-amulet": {"name": 1, "price": "1400", "attr_": ["['+', '20', 'Attack', 'Speed']"], "buildto": ["Builds into 2,800 1,950"], "buildfrom": [], "description": ["Active:", "Fade", "Grants", "invisibility", "to", "you", "or", "a", "target", "allied", "hero", "as", "long", "as", "the", "target", "unit", "remains", "still.", "Has", "a", "1.25", "second", "fade", "time,", "and", "breaks", "instantly", "upon", "moving.", "There", "is", "no", "cooldown", "when", "using", "this", "item", "on", "yourself.", "Range:", "600", "7"], "position": []}, "shadow-blade": {"name": 1, "price": "2800", "attr_": ["['+', '22', 'Damage', '+', '30', 'Attack', 'Speed']"], "buildto": ["Builds into 5,550"], "buildfrom": ["Builds from 1,400 1,400"], "description": ["Active:", "Shadow", "Walk", "Makes", "you", "invisible", "for", "14.0", "seconds,", "or", "until", "you", "attack", "or", "cast", "a", "spell.", "While", "Shadow", "Walk", "is", "active,", "you", "move", "20%", "faster", "and", "can", "move", "through", "units.", "If", "attacking", "to", "end", "the", "invisibility,", "you", "gain", "175", "bonus", "physical", "damage", "on", "that", "attack.", "28", "75"], "position": []}, "shivas-guard": {"name": 1, "price": "4750", "attr_": ["['+', '30', 'Intelligence', '+', '15', 'Armor']"], "buildto": [], "buildfrom": ["Builds from 1,400 2,700 650"], "description": ["Active:", "Arctic", "Blast", "Emits", "a", "freezing", "wave", "that", "deals", "200", "magical", "damage", "to", "enemies", "and", "slows", "their", "movement", "by", "-40%", "for", "4.0", "seconds.", "Radius:", "900", "Passive:", "Freezing", "Aura", "Reduces", "the", "attack", "speed", "of", "all", "enemies", "by", "-45", ".", "Radius:", "1200", "30", "100"], "position": []}, "silver-edge": {"name": 1, "price": "5550", "attr_": ["['+', '30', 'Damage', '+', '30', 'Attack', 'Speed', '+', '15', 'All', 'Attributes']"], "buildto": [], "buildfrom": ["Builds from 2,150 2,800 600"], "description": ["Active:", "Shadow", "Walk", "Makes", "you", "invisible", "for", "14.0", "seconds,", "or", "until", "you", "attack", "or", "cast", "a", "spell.", "While", "invisible,", "you", "move", "25%", "faster", "and", "can", "move", "through", "units.", "Attacking", "to", "end", "the", "invisibility", "will", "deal", "175", "bonus", "physical", "damage", "to", "the", "target,", "and", "for", "4.0", "seconds,", "disable", "their", "passive", "abilities.", "22", "75"], "position": []}, "skull-basher": {"name": 1, "price": "2950", "attr_": ["['+', '25', 'Damage', '+', '10', 'Strength']"], "buildto": ["Builds into 6,650"], "buildfrom": ["Builds from 1,600 450 900"], "description": ["Passive:", "Bash", "Grants", "melee", "heroes", "a", "25%", "chance", "on", "hit", "to", "stun", "the", "target", "for", "1.5", "seconds", "and", "deal", "100", "bonus", "magical", "damage.", "Bash", "chance", "for", "ranged", "heroes", "is", "10%", ".", "2.3"], "position": []}, "slippers-of-agility": {"name": 1, "price": "135", "attr_": ["['+', '3', 'Agility']"], "buildto": ["Builds into 515"], "buildfrom": [], "description": [], "position": []}, "smoke-of-deceit": {"name": 1, "price": "80", "attr_": [], "buildto": [], "buildfrom": [], "description": ["Use:", "Disguise", "Turns", "the", "caster", "and", "all", "allied", "player-controlled", "units", "in", "a", "1200", "radius", "invisible,", "and", "grants", "15%", "bonus", "movement", "speed", "for", "35.0", "seconds.", "Attacking,", "or", "moving", "within", "1025", "range", "of", "an", "enemy", "hero", "or", "tower,", "will", "break", "the", "invisibility.", "Disguise", "grants", "invisibility", "that", "is", "immune", "to", "True", "Sight.", "1"], "position": []}, "solar-crest": {"name": 1, "price": "3875", "attr_": ["['+', '12', 'Armor', '+', '10', 'All', 'Attributes', '+', '20', 'Movement', 'Speed', '+', '1.5', 'Mana', 'Regeneration']"], "buildto": [], "buildfrom": ["Builds from 2,150 1,175 300 250"], "description": ["Active:", "Shine", "When", "cast", "on", "an", "ally,", "grants", "them", "12", "armor,", "80", "attack", "speed,", "and", "10%", "movement", "speed.", "When", "cast", "on", "an", "enemy,", "removes", "12", "armor,", "80", "attack", "speed,", "and", "10%", "movement", "speed.", "Removes", "the", "armor", "from", "the", "caster", "when", "used.", "Cannot", "target", "magic", "immune", "enemies.", "Range:", "1000", "7"], "position": []}, "soul-booster": {"name": 1, "price": "3200", "attr_": ["['+', '425', 'Health', '+', '425', 'Mana']"], "buildto": ["Builds into 4,900 5,900"], "buildfrom": ["Builds from 900 1,200 1,100"], "description": [], "position": []}, "soul-ring": {"name": 1, "price": "770", "attr_": ["['+', '6', 'Strength', '+', '2.5', 'HP', 'Regeneration']"], "buildto": [], "buildfrom": ["Builds from 135 135 300 200"], "description": ["Active:", "Sacrifice", "Consume", "170", "health", "to", "temporarily", "gain", "150", "mana.", "Lasts", "10", "seconds.", "If", "the", "mana", "gained", "cannot", "fit", "in", "your", "mana", "pool,", "it", "creates", "a", "buffer", "of", "mana", "that", "will", "be", "used", "before", "your", "mana", "pool.", "25"], "position": []}, "spirit-vessel": {"name": 1, "price": "2975", "attr_": ["['+', '250', 'Health', '+', '20', 'Movement', 'Speed', '+', '1.5', 'Mana', 'Regeneration', '+', '2', 'All', 'Attributes', '+', '2.0', 'Armor']"], "buildto": [], "buildfrom": ["Builds from 1,100 875 250 750"], "description": ["Active:", "Soul", "Release", "When", "used", "against", "enemies,", "it", "reduces", "health", "by", "4.0%", "of", "current", "health", "per", "second,", "and", "reduces", "HP", "regeneration", "and", "healing", "by", "60%", ".", "Deals", "25", "damage", "per", "second.", "When", "used", "on", "allies,", "it", "provides", "30", "health", "regeneration", "per", "second.", "Lasts", "8.0", "seconds.", "Gains", "charges", "every", "time", "an", "enemy", "hero", "dies", "within", "1400", "units.", "Only", "the", "closest", "Spirit", "Vessel", "to", "the", "dying", "hero", "will", "gain", "a", "charge.", "Cast", "Range:", "950", "7"], "position": []}, "staff-of-wizardry": {"name": 1, "price": "1000", "attr_": ["['+', '10', 'Intelligence']"], "buildto": ["Builds into 2,750 2,250 2,700 4,200 2,750 2,625 2,050"], "buildfrom": [], "description": [], "position": []}, "stout-shield": {"name": 1, "price": "200", "attr_": [], "buildto": ["Builds into 2,150"], "buildfrom": [], "description": ["Passive:", "Damage", "Block", "Grants", "a", "50%", "chance", "to", "block", "20", "damage", "from", "incoming", "attacks", "on", "melee", "heroes,", "and", "9", "damage", "on", "ranged."], "position": []}, "super-blink-dagger": {"name": 1, "price": [], "attr_": [], "buildto": [], "buildfrom": [], "description": ["Active:", "Blink", "Teleport", "to", "a", "target", "point", "up", "to", "1200", "units", "away.", "15"], "position": []}, "talisman-of-evasion": {"name": 1, "price": "1400", "attr_": ["['+', '15%', 'Evasion']"], "buildto": ["Builds into 5,475 3,450"], "buildfrom": [], "description": [], "position": []}, "tango-shared": {"name": 1, "price": "30", "attr_": [], "buildto": [], "buildfrom": [], "description": ["Use:", "Devour", "Consumes", "a", "target", "tree", "to", "gain", "7.0", "health", "regeneration", "for", "16.0", "seconds.", "Consuming", "a", "ward", "or", "Ironwood", "Tree", "doubles", "the", "heal", "amount.", "Range:", "165", "Ward", "Range:", "450", "60"], "position": []}, "tango": {"name": 1, "price": "90", "attr_": [], "buildto": [], "buildfrom": [], "description": ["Use:", "Devour", "Consumes", "a", "target", "tree", "to", "gain", "7.0", "health", "regeneration", "for", "16.0", "seconds.", "Consuming", "a", "ward", "or", "Ironwood", "Tree", "doubles", "the", "heal", "amount.", "Comes", "with", "3", "charges.", "Can", "be", "used", "on", "an", "allied", "hero", "to", "give", "them", "one", "Tango.", "Range:", "165", "Ward", "Range:", "450"], "position": []}, "tome-of-knowledge": {"name": 1, "price": "150", "attr_": [], "buildto": [], "buildfrom": [], "description": ["Use:", "Enlighten", "Grants", "you", "700", "experience", "plus", "135", "per", "tome", "consumed", "by", "your", "team", "after", "the", "first", "two.", "Tomes", "Used", "By", "Team:", "0", "300"], "position": []}, "tranquil-boots": {"name": 1, "price": "1050", "attr_": ["['+', '26%', 'Movement', 'Speed', '+', '16', 'HP', 'Regeneration']"], "buildto": [], "buildfrom": ["Builds from 300 500 250"], "description": ["Passive:", "Break", "Whenever", "you", "attack", "a", "hero", "or", "are", "attacked", "by", "any", "unit,", "the", "bonus", "16", "HP", "regen", "is", "lost", "and", "the", "movement", "speed", "bonus", "is", "reduced", "to", "18%", "for", "13", "seconds.", "Movement", "speed", "bonuses", "from", "multiple", "pairs", "of", "boots", "do", "not", "stack.", "13"], "position": []}, "ultimate-orb": {"name": 1, "price": "2150", "attr_": ["['+', '10', 'All', 'Attributes']"], "buildto": ["Builds into 5,700 5,050 4,700 5,500 3,875 5,550"], "buildfrom": [], "description": [], "position": []}, "urn-of-shadows": {"name": 1, "price": "875", "attr_": ["['+', '1.5', 'Mana', 'Regeneration', '+', '2', 'All', 'Attributes', '+', '2.0', 'Armor']"], "buildto": ["Builds into 2,975"], "buildfrom": ["Builds from 175 165 310 225"], "description": ["Active:", "Soul", "Release", "Provides", "30", "health", "regeneration", "when", "cast", "on", "allies,", "and", "deals", "25", "damage", "per", "second", "when", "cast", "on", "enemies.", "Lasts", "8.0", "seconds.", "Gains", "charges", "every", "time", "an", "enemy", "hero", "dies", "within", "1400", "units.", "Only", "the", "closest", "Urn", "to", "the", "dying", "hero", "will", "gain", "a", "charge.", "Cast", "Range:", "950", "7"], "position": []}, "vanguard": {"name": 1, "price": "2150", "attr_": ["['+', '250', 'Health', '+', '7.0', 'HP', 'Regeneration']"], "buildto": ["Builds into 6,650 3,700"], "buildfrom": ["Builds from 850 1,100 200"], "description": ["Passive:", "Damage", "Block", "Grants", "a", "50%", "chance", "to", "block", "70", "damage", "from", "incoming", "attacks", "on", "melee", "heroes,", "and", "35", "damage", "on", "ranged."], "position": []}, "veil-of-discord": {"name": 1, "price": "2050", "attr_": ["['+', '6', 'HP', 'Regeneration', '+', '6', 'Armor', '+', '6', 'Agility', '+', '6', 'Strength', '+', '15', 'Intelligence']"], "buildto": [], "buildfrom": ["Builds from 900 700 450"], "description": ["Active:", "Magic", "Weakness", "Cast", "a", "600", "radius", "blast", "that", "decreases", "enemy", "magic", "resistance", "by", "-25%", ".", "Range:", "1000", "Duration:", "16.0", "seconds.", "20", "50"], "position": []}, "vitality-booster": {"name": 1, "price": "1100", "attr_": ["['+', '250', 'Health']"], "buildto": ["Builds into 5,200 2,150 3,200 3,100 2,975"], "buildfrom": [], "description": [], "position": []}, "vladmirs-offering": {"name": 1, "price": "1925", "attr_": [], "buildto": [], "buildfrom": ["Builds from 900 525 500"], "description": ["Passive:", "Vladmir's", "Aura", "Grants", "lifesteal", "(15%", "for", "melee", "heroes,", "10%", "for", "ranged),", "1.5", "mana", "regeneration,", "15%", "bonus", "attack", "damage,", "and", "4", "armor", "to", "nearby", "allies.", "Radius:", "1200"], "position": []}, "void-stone": {"name": 1, "price": "850", "attr_": ["['+', '1.75', 'Mana', 'Regeneration']"], "buildto": ["Builds into 1,700 5,700 2,750 2,350"], "buildfrom": [], "description": [], "position": []}, "wind-lace": {"name": 1, "price": "250", "attr_": ["['+', '20', 'Movement', 'Speed']"], "buildto": ["Builds into 2,750 1,625 1,050 3,875 2,975"], "buildfrom": [], "description": ["Bonuses", "from", "multiple", "Wind", "Laces", "do", "not", "stack."], "position": []}, "wraith-band": {"name": 1, "price": "515", "attr_": ["['+', '3', 'Strength', '+', '6', 'Agility', '+', '3', 'Intelligence', '+', '5', 'Attack', 'Speed']"], "buildto": [], "buildfrom": ["Builds from 135 165 215"], "description": [], "position": []}, "yasha-and-kaya": {"name": 1, "price": "4100", "attr_": ["['+', '16', 'Agility', '+', '16', 'Intelligence', '+', '16', 'Attack', 'Speed', '+', '16%', 'Manacost', 'and', 'Manaloss', 'Reduction', '+', '30', 'Movement', 'Speed', '+', '12%', 'Spell', 'Amplification']"], "buildto": [], "buildfrom": ["Builds from 2,050 2,050"], "description": [], "position": []}, "yasha": {"name": 1, "price": "2050", "attr_": ["['+', '16', 'Agility', '+', '12', 'Attack', 'Speed', '+', '20', 'Movement', 'Speed']"], "buildto": ["Builds into 4,700 4,100 4,100"], "buildfrom": ["Builds from 450 1,000 600"], "description": [], "position": []}}